mlogium/__init__.py
mlogium/__main__.py
mlogium/abi.py
mlogium/builtins.py
mlogium/cli.py
mlogium/compilation_context.py
mlogium/compile.py
mlogium/compiler.py
mlogium/enums.py
mlogium/error.py
mlogium/instruction.py
mlogium/lexer.py
mlogium/linker.py
mlogium/linking_context.py
mlogium/macro.py
mlogium/macro_impl.py
mlogium/node.py
mlogium/optimizer.py
mlogium/parser.py
mlogium/scope.py
mlogium/tokens.py
mlogium/util.py
mlogium/value.py
mlogium/value_types.py
mlogium/stdlib/gen.mu
mlogium/stdlib/math.mu
mlogium-0.0.1.dist-info/LICENSE
mlogium-0.0.1.dist-info/METADATA
mlogium-0.0.1.dist-info/WHEEL
mlogium-0.0.1.dist-info/entry_points.txt
mlogium-0.0.1.dist-info/top_level.txt
mlogium-0.0.1.dist-info/RECORD
