Metadata-Version: 2.1
Name: mlogium
Version: 0.0.1
Summary: high level mindustry logic language
Home-page: https://github.com/albi-c/mlogium
Author: albi-c
Project-URL: Documentation, https://github.com/albi-c/mlogium/wiki
Project-URL: Bug Tracker, https://github.com/albi-c/mlogium/issues
Classifier: Programming Language :: Python :: 3.12
Classifier: Programming Language :: Python :: 3.13
Classifier: License :: OSI Approved :: MIT License
Classifier: Operating System :: OS Independent
Requires-Python: >=3.12
License-File: LICENSE
Requires-Dist: pyperclip >=1.9.0
